altogether/__init__.py
altogether-0.1.0.dist-info/METADATA
altogether-0.1.0.dist-info/WHEEL
altogether-0.1.0.dist-info/top_level.txt
altogether-0.1.0.dist-info/RECORD
