Metadata-Version: 2.4
Name: altogether
Version: 0.1.0
Summary: Add your description here
Author: Sunghyun Cho
Author-email: hey@cho.sh
Requires-Python: >=3.7
Dynamic: author
Dynamic: author-email
Dynamic: requires-python
